<Properties StartupConfiguration="{9C360207-CA20-40EB-B72A-435A2B18C53D}|Default">
  <MonoDevelop.Ide.Workbench>
    <Files>
      <File FileName="RpsDemo.HardCodedFrag/TranslateActivity.cs" Line="4" Column="1" />
      <File FileName="RpsDemo.HardCodedFrag/TextFrag.cs" Line="25" Column="25" />
      <File FileName="RpsDemo.HardCodedFrag/HandFrag.cs" Line="1" Column="1" />
      <File FileName="RpsDemo.HardCodedFrag/MainActivity.cs" Line="26" Column="57" />
    </Files>
  </MonoDevelop.Ide.Workbench>
  <MonoDevelop.Ide.Workspace ActiveConfiguration="Debug" />
  <MonoDevelop.Ide.DebuggingService.Breakpoints>
    <BreakpointStore />
  </MonoDevelop.Ide.DebuggingService.Breakpoints>
  <MonoDevelop.Ide.DebuggingService.PinnedWatches />
  <MonoDevelop.Ide.ItemProperties.RpsDemo.HardCodedFrag AndroidDesignerPreferredDevice="Nexus 4" PreferredExecutionTarget="Android.Nexus_5_x86_API_19" HideGettingStarted="True" />
  <MultiItemStartupConfigurations />
  <MonoDevelop.Ide.ItemProperties.RpsDemo.DynamicFragLoad AndroidDesignerPreferredDevice="Nexus 4" PreferredExecutionTarget="Android.Nexus5-API23-x86_64" HideGettingStarted="True" />
</Properties>